that_nlp_library/__init__.py
that_nlp_library/_modidx.py
that_nlp_library/evaluations.py
that_nlp_library/model_lm_main.py
that_nlp_library/model_main.py
that_nlp_library/text_augmentation.py
that_nlp_library/text_main.py
that_nlp_library/text_main_lm.py
that_nlp_library/text_main_lm_streaming.py
that_nlp_library/text_main_streaming.py
that_nlp_library/text_transformation.py
that_nlp_library/utils.py
that_nlp_library/models/__init__.py
that_nlp_library/models/gpt2/__init__.py
that_nlp_library/models/gpt2/classifiers.py
that_nlp_library/models/roberta/__init__.py
that_nlp_library/models/roberta/classifiers.py
that_nlp_library/models/roberta/conditional_prob_classifiers.py
that_nlp_library/models/roberta/deep_hierarchical_classifiers.py
that_nlp_library-0.2.2.dist-info/LICENSE
that_nlp_library-0.2.2.dist-info/METADATA
that_nlp_library-0.2.2.dist-info/WHEEL
that_nlp_library-0.2.2.dist-info/entry_points.txt
that_nlp_library-0.2.2.dist-info/top_level.txt
that_nlp_library-0.2.2.dist-info/RECORD
