Metadata-Version: 2.1
Name: that-nlp-library
Version: 0.2.2
Summary: Aim to be a convenient NLP library with the help from HuggingFace
Home-page: https://github.com/anhquan0412/that-nlp-library
Author: Quan Tran
Author-email: anhquan0412@gmail.com
License: Apache Software License 2.0
Keywords: nbdev,python,nlp,natural language processing,transformer,deep learning,envibert,roberta,gpt2,phobert
Classifier: Development Status :: 4 - Beta
Classifier: Intended Audience :: Developers
Classifier: Natural Language :: English
Classifier: Programming Language :: Python :: 3.9
Classifier: Programming Language :: Python :: 3.10
Classifier: License :: OSI Approved :: Apache Software License
Requires-Python: >=3.9
License-File: LICENSE
Requires-Dist: matplotlib
Requires-Dist: pandas
Requires-Dist: requests
Requires-Dist: tqdm
Requires-Dist: scikit-learn
Requires-Dist: datasets
Requires-Dist: underthesea
Requires-Dist: dill
Requires-Dist: transformers
Requires-Dist: sentencepiece
Requires-Dist: pyarrow
Requires-Dist: unidecode
Requires-Dist: wandb
Requires-Dist: evaluate
Requires-Dist: accelerate
Provides-Extra: dev
